{"layers":[{"name":"ambience","x":640,"y":360,"width":1280,"height":720},{"name":"back_door_motel","x":834,"y":351,"width":160,"height":268},{"name":"back_switch_lamp1","x":958,"y":355,"width":64,"height":64},{"name":"back_switch_off_lamp1","x":958,"y":355,"width":64,"height":64},{"name":"back_sky","x":500,"y":393,"width":272,"height":178},{"name":"back_window","x":498,"y":393,"width":300,"height":196},{"name":"back_louvers","x":499,"y":385,"width":306,"height":216},{"name":"back_wire","x":696,"y":374,"width":78,"height":88},{"name":"back_luk","x":696,"y":374,"width":78,"height":86},{"name":"back_light_window","x":497,"y":368,"width":478,"height":368},{"name":"back_shadow_lamp","x":498,"y":196,"width":110,"height":34},{"name":"back_bed2_shadow","x":975,"y":184,"width":520,"height":224},{"name":"back_chair_shadow","x":242,"y":195,"width":298,"height":224},{"name":"back_chair","x":312,"y":199,"width":164,"height":224},{"name":"back_bed2","x":917,"y":185,"width":424,"height":222},{"name":"back_fbox","x":1065,"y":90,"width":104,"height":86},{"name":"back_fbox_open_wire","x":1065,"y":149,"width":34,"height":92},{"name":"back_fbox_open_doll","x":1065,"y":191,"width":110,"height":80},{"name":"back_fbox_open","x":1064,"y":115,"width":162,"height":136},{"name":"back_fbox","x":1065,"y":90,"width":104,"height":86},{"name":"back_table_shadow","x":518,"y":167,"width":262,"height":82},{"name":"back_table","x":517,"y":180,"width":248,"height":130},{"name":"back_light_lamp2","x":563,"y":164,"width":808,"height":328},{"name":"back_lamp","x":497,"y":139,"width":72,"height":222},{"name":"back_switch_lamp2","x":483,"y":155,"width":58,"height":94},{"name":"back_switch_off_lamp2","x":483,"y":165,"width":58,"height":74},{"name":"back_light_lamp2a","x":495,"y":230,"width":560,"height":460},{"name":"back_lamp3","x":658,"y":696,"width":72,"height":48},{"name":"back_cooler1","x":659,"y":682,"width":310,"height":20},{"name":"back_cooler2","x":659,"y":682,"width":310,"height":20},{"name":"back_light_lamp1","x":647,"y":484,"width":752,"height":472},{"name":"nightstand1","x":421,"y":244,"width":158,"height":94},{"name":"phone","x":399,"y":326,"width":76,"height":70},{"name":"trubka","x":399,"y":357,"width":112,"height":38},{"name":"shkaf","x":654,"y":384,"width":228,"height":362},{"name":"nightstand2","x":863,"y":244,"width":158,"height":94},{"name":"shadow_nightstand2","x":932,"y":266,"width":296,"height":142},{"name":"light_lamp2","x":563,"y":272,"width":808,"height":438},{"name":"shadow_lamp","x":498,"y":196,"width":110,"height":34},{"name":"lamp","x":497,"y":302,"width":72,"height":222},{"name":"switch_lamp2","x":483,"y":318,"width":58,"height":94},{"name":"switch_off_lamp2","x":483,"y":328,"width":58,"height":74},{"name":"light_lamp2a","x":495,"y":365,"width":560,"height":518},{"name":"bed2_shadow","x":962,"y":217,"width":494,"height":222},{"name":"shadow_nightstand1","x":351,"y":266,"width":296,"height":142},{"name":"chair_shadow","x":218,"y":196,"width":322,"height":224},{"name":"chair","x":312,"y":199,"width":164,"height":224},{"name":"bed2","x":917,"y":218,"width":424,"height":222},{"name":"table_shadow","x":518,"y":41,"width":262,"height":82},{"name":"table","x":517,"y":128,"width":248,"height":130},{"name":"plant","x":864,"y":345,"width":60,"height":110},{"name":"lamp3","x":658,"y":696,"width":72,"height":48},{"name":"cooler1","x":659,"y":682,"width":310,"height":20},{"name":"cooler2","x":659,"y":682,"width":310,"height":20},{"name":"light_lamp1","x":647,"y":484,"width":752,"height":472}]}